{
  "last_run": "2026-02-17T21:18:54.796819+00:00",
  "scans": {
    "positions": {
      "sentiment_score": 25,
      "trend": "falling",
      "volume": "high",
      "key_narratives": [
        "Bitcoin 30% decline triggers 'crypto winter' headlines despite fundamental strength",
        "Institutional adoption accelerating (asset managers hiring crypto leadership at $350K)",
        "DeFi protocols generating real revenue; profitable projects separating from speculators",
        "Market consolidation phase with weak projects failing and strong ones accelerating",
        "Macro catalyst: US Supreme Court tariff ruling February 20 expected to trigger volatility"
      ],
      "risk_signals": [
        "Extreme fear sentiment at 4-year low[4]",
        "Bitcoin down 30% in worst week since 2022, trading below $70K resistance[2][3]",
        "Weak derivatives and lower Open Interest weighing on major cryptocurrencies[3]",
        "Capital flowing away from crypto toward AI and commodities[3]",
        "Ethereum struggling in $1,937\u2013$2,023 range; XRP testing support levels[3]"
      ],
      "notable_mentions": 0,
      "token": "positions",
      "scanned_at": "2026-02-17T20:33:59.869906+00:00"
    },
    "BTC": {
      "sentiment_score": 32,
      "trend": "falling",
      "volume": "high",
      "key_narratives": [
        "Fear and uncertainty dominating market psychology (85% negative sentiment)",
        "Key support level breaks triggering sell pressure",
        "Network activity declining amid broader market weakness",
        "Bitcoin dominance at 60% with elevated trading activity ($117.2B in 24h volume)",
        "Technical indicators showing sustained downside pressure across timeframes"
      ],
      "risk_signals": [
        "Extreme Fear & Greed Index score of 12 across crypto market",
        "Bitcoin down 14.71% over last month, recent 6-month low hit",
        "High FUD levels among retail investors on social media platforms",
        "Bearish technical setup with price below 50-day and 200-day SMAs",
        "Volume surge (42% gain) coinciding with price decline suggests capitulation selling"
      ],
      "notable_mentions": 2,
      "token": "BTC",
      "scanned_at": "2026-02-17T21:03:58.464772+00:00"
    },
    "ETH": {
      "sentiment_score": 54,
      "trend": "falling",
      "volume": "high",
      "key_narratives": [
        "Institutional accumulation despite price weakness below $2,000",
        "Market volatility and margin call concerns for crypto treasury firms",
        "Long-term holder conviction amid bearish short-term sentiment",
        "Tokenization and Wall Street adoption potential via Robinhood Chain",
        "Technical divergence patterns suggesting potential recovery scenarios"
      ],
      "risk_signals": [
        "ETH dropped to $1,895 intraday on February 12 amid bearish sentiment",
        "$85.1 million in outflows recorded",
        "20% monthly decline pushing price below $2,000 support",
        "Crypto treasury firms facing margin call pressure and forced selling risk",
        "Standard Chartered lowered year-end target from $7,000 to $4,000",
        "Downside risk to $1,747 if $1,937 support breaks",
        "Weak U.S. sentiment driving week 4 of sustained outflows"
      ],
      "notable_mentions": 3,
      "token": "ETH",
      "scanned_at": "2026-02-17T21:04:05.001745+00:00"
    },
    "SOL": {
      "sentiment_score": 25,
      "trend": "falling",
      "volume": "normal",
      "key_narratives": [
        "Strong fundamentals like record $1.66B RWA tokenization and upcoming upgrades (Alpenglow, Firedancer) contrasting weak price action around $85-86[1][2]",
        "Extreme fear sentiment with Fear & Greed Index at 12, bearish technicals below key EMAs and supports[1][2][3]",
        "Positive hype on institutional adoption (Morgan Stanley loading SOL) and recovery predictions to $95-120[5][6]"
      ],
      "risk_signals": [
        "31% YTD price drop, bearish doji, potential breakdown below $80-85 support[1][2][4]",
        "Persistent outflows from crypto funds despite some SOL inflows, weak U.S. sentiment[7][8]",
        "Selling pressure and negative funding rates[4]"
      ],
      "notable_mentions": 0,
      "token": "SOL",
      "scanned_at": "2026-02-17T21:19:03.301420+00:00"
    },
    "BNB": {
      "sentiment_score": 58,
      "trend": "rising",
      "volume": "normal",
      "key_narratives": [
        "Cautiously Bullish - RSI Reset and Short Squeeze Potential",
        "Ecosystem Maturity and Intrinsic Utility Value",
        "Capital Rotation from BNB to Emerging Alternatives",
        "Support Level Stability at $630-$640 Zone",
        "Institutional Adoption and DEX Dominance"
      ],
      "risk_signals": [
        "Weekly volatility (-17.97% drop observed)",
        "Regulatory uncertainty in various jurisdictions",
        "Capital flight to presales ($2.5B influx noted)",
        "Mixed macroeconomic signals (inflation and consumer confidence)",
        "Price range compression suggesting indecision"
      ],
      "notable_mentions": 3,
      "token": "BNB",
      "scanned_at": "2026-02-17T21:19:09.018602+00:00"
    }
  },
  "total_signals": 52
}